{
    "x": {
        "(D11_V1,O11,T2)": 1.0,
        "(D11_V1,T1,T8)": 1.0,
        "(D11_V1,T2,T5)": 1.0,
        "(D11_V1,T8,T10)": 1.0,
        "(D11_V1,T9,D11)": 1.0,
        "(D11_V1,T5,C6)": 1.0,
        "(D11_V1,T10,C8)": 1.0,
        "(D11_V1,C6,T1)": 1.0,
        "(D11_V1,C8,T9)": 1.0,
        "(D12_V1,O12,T4)": 1.0,
        "(D12_V1,T3,T6)": 1.0,
        "(D12_V1,T4,T7)": 1.0,
        "(D12_V1,T7,T3)": 1.0,
        "(D12_V1,T6,D12)": 1.0
    },
    "T": {
        "(D11_V1,T5)": 390.066,
        "(D12_V1,C4)": 210.0,
        "(D11_V1,T10)": 559.325,
        "(D12_V1,T2)": 430.0,
        "(D11_V1,C3)": 644.0,
        "(D11_V1,C5)": 359.0,
        "(D11_V1,D11)": 10000.0,
        "(D12_V1,C6)": 324.0,
        "(D12_V1,T7)": 333.0,
        "(D12_V1,T4)": 308.391,
        "(D11_V1,T3)": 500.0,
        "(D12_V1,C1)": 155.0,
        "(D11_V1,T8)": 526.089,
        "(D11_V1,T9)": 642.4966,
        "(D12_V1,T6)": 380.0017,
        "(D11_V1,C6)": 430.0742,
        "(D12_V1,C8)": 402.0,
        "(D12_V1,C7)": 417.0,
        "(D12_V1,D12)": 10000.0,
        "(D11_V1,C4)": 610.0,
        "(D12_V1,T5)": 628.0,
        "(D12_V1,C2)": 149.0,
        "(D11_V1,T2)": 348.9412,
        "(D12_V1,T1)": 57.0,
        "(D12_V1,T10)": 417.0,
        "(D12_V1,C5)": 359.0,
        "(D12_V1,C3)": 644.0,
        "(D11_V1,T7)": 333.0,
        "(D11_V1,C1)": 155.0,
        "(D11_V1,T4)": 150.0,
        "(D12_V1,T3)": 365.2895,
        "(D12_V1,T8)": 359.0,
        "(D12_V1,T9)": 424.0,
        "(D11_V1,T6)": 207.0,
        "(D11_V1,C7)": 417.0,
        "(D11_V1,C8)": 636.6656,
        "(D11_V1,C2)": 149.0,
        "(D11_V1,T1)": 457.0
    },
    "w": {},
    "E_pre": {
        "(D11_V1,T5)": 191.2305,
        "(D11_V1,C2)": 10.0,
        "(D12_V1,C4)": 10.0,
        "(D11_V1,T10)": 131.9739,
        "(D12_V1,T2)": 46.9622,
        "(D11_V1,C3)": 10.0,
        "(D11_V1,C5)": 10.0,
        "(D11_V1,D11)": 248.2681,
        "(D12_V1,T7)": 239.2903,
        "(D12_V1,T4)": 271.2821,
        "(D11_V1,T3)": 311.772,
        "(D12_V1,C1)": 10.0,
        "(D11_V1,T8)": 175.1808,
        "(D11_V1,T9)": 292.4198,
        "(D12_V1,T6)": 178.188,
        "(D11_V1,C6)": 139.2199,
        "(D12_V1,C8)": 10.0,
        "(D12_V1,C7)": 10.0,
        "(D12_V1,D12)": 111.0699,
        "(D11_V1,C4)": 10.0,
        "(D12_V1,T5)": 29.6446,
        "(D12_V1,C2)": 10.0,
        "(D11_V1,T2)": 244.6927,
        "(D12_V1,T1)": 68.0237,
        "(D12_V1,T10)": 72.9044,
        "(D12_V1,C5)": 10.0,
        "(D12_V1,C3)": 10.0,
        "(D11_V1,T7)": 311.6276,
        "(D11_V1,C1)": 10.0,
        "(D11_V1,T4)": 30.1533,
        "(D12_V1,T3)": 197.3139,
        "(D12_V1,T8)": 40.3,
        "(D12_V1,T9)": 29.3293,
        "(D11_V1,T6)": 354.1181,
        "(D11_V1,C7)": 10.0,
        "(D11_V1,C8)": 31.4311,
        "(D12_V1,C6)": 10.0,
        "(D11_V1,T1)": 264.9964
    },
    "E_bar": {
        "(D11_V1,T5)": 161.5859,
        "(D11_V1,C2)": 300.0,
        "(D12_V1,C4)": 300.0,
        "(D11_V1,T10)": 59.0695,
        "(D11_V1,C3)": 300.0,
        "(D11_V1,C5)": 300.0,
        "(D12_V1,T7)": 227.6628,
        "(D12_V1,T4)": 241.1288,
        "(D11_V1,T3)": 300.0,
        "(D12_V1,C1)": 300.0,
        "(D11_V1,T8)": 134.8808,
        "(D11_V1,T9)": 263.0904,
        "(D12_V1,T6)": 124.0699,
        "(D11_V1,C6)": 300.0,
        "(D12_V1,C8)": 300.0,
        "(D12_V1,C7)": 300.0,
        "(D11_V1,C4)": 300.0,
        "(D11_V1,O11)": 300.0,
        "(D12_V1,O12)": 300.0,
        "(D12_V1,C2)": 300.0,
        "(D11_V1,T2)": 197.7305,
        "(D12_V1,C5)": 300.0,
        "(D12_V1,C3)": 300.0,
        "(D11_V1,T7)": 300.0,
        "(D11_V1,C1)": 300.0,
        "(D12_V1,T3)": 185.5419,
        "(D11_V1,T6)": 300.0,
        "(D11_V1,C7)": 300.0,
        "(D11_V1,C8)": 300.0,
        "(D12_V1,C6)": 300.0,
        "(D11_V1,T1)": 196.9728
    },
    "G": {
        "(D11_V1,T5)": 29.6446,
        "(D11_V1,T10)": 72.9044,
        "(D12_V1,T2)": 46.9622,
        "(D12_V1,T7)": 11.6276,
        "(D12_V1,T4)": 30.1533,
        "(D11_V1,T3)": 11.772,
        "(D11_V1,T8)": 40.3,
        "(D11_V1,T9)": 29.3293,
        "(D12_V1,T6)": 54.1181,
        "(D12_V1,T5)": 29.6446,
        "(D11_V1,T2)": 46.9622,
        "(D12_V1,T1)": 68.0237,
        "(D12_V1,T10)": 72.9044,
        "(D11_V1,T7)": 11.6276,
        "(D11_V1,T4)": 30.1533,
        "(D12_V1,T3)": 11.772,
        "(D12_V1,T8)": 40.3,
        "(D12_V1,T9)": 29.3293,
        "(D11_V1,T6)": 54.1181,
        "(D11_V1,T1)": 68.0237
    },
    "CT": {
        "(D11_V1,C6)": 446.1522,
        "(D11_V1,C8)": 663.5225
    },
    "Y": {
        "(C1,D11_V1,D12_V1)": 1.0,
        "(C2,D11_V1,D12_V1)": 1.0,
        "(C3,D12_V1,D11_V1)": 1.0,
        "(C4,D11_V1,D12_V1)": 1.0,
        "(C4,D12_V1,D11_V1)": 1.0,
        "(C5,D12_V1,D11_V1)": 1.0,
        "(C6,D11_V1,D12_V1)": 1.0,
        "(C7,D11_V1,D12_V1)": 1.0,
        "(C8,D11_V1,D12_V1)": 1.0
    }
}